setup.cfg
setup.py
loveseat/__init__.py
loveseat/__main__.py
loveseat/aggregated_result.py
loveseat/cli.py
loveseat/couch_runners.py
loveseat/couch_specs.py
loveseat/couch_test.py
loveseat/loveseat.py
loveseat/result.py
loveseat/suite.py
loveseat/test_runner.py
loveseat/utils.py
loveseat.egg-info/PKG-INFO
loveseat.egg-info/SOURCES.txt
loveseat.egg-info/dependency_links.txt
loveseat.egg-info/entry_points.txt
loveseat.egg-info/pbr.json
loveseat.egg-info/requires.txt
loveseat.egg-info/top_level.txt
tests/__init__.py
tests/test_aggregated_result.py
tests/test_couch_specs.py
tests/test_test_runner.py