Metadata-Version: 1.0
Name: loveseat
Version: 0.0.5
Summary: Benchmark library for testing CouchDB
Home-page: http://github.com/dimagi/loveseat
Author: Dimagi
Author-email: dev@dimagi.com
License: MIT
Platform: UNKNOWN
